{"greeting": "Greetings from The On-Line Encyclopedia of Integer Sequences! http://oeis.org/", "query": "id:A033763", "count": 1, "start": 0, "results": [{"number": 33763, "data": "1,1,1,2,1,2,3,3,1,2,3,1,5,3,2,4,4,3,3,3,3,5,3,2,5,5,3,8,2,2,7,4,3,6,6,4,5,3,3,5,7,3,8,4,3,10,6,6,6,4,3,5,10,2,5,7,4,10,3,4,9,9,5,8,3,4,9,7,5,9,9,5,9,5,3,10,6,4,9,5,7,9,10,5,6,7,5", "name": "Product t2(q^d); d | 4, where t2 = theta2(q)/(2*q^(1/4)).", "comment": ["Also the number of positive odd solutions to equation a^2 + 2*b^2 + 4*c^2 = 8*n + 7. - _Seiichi Manyama_, May 29 2017"], "link": ["Seiichi Manyama, <a href=\"/A033763/b033763.txt\">Table of n, a(n) for n = 0..10000</a>"], "keyword": "nonn", "offset": "0,4", "author": "_N. J. A. Sloane_", "ext": ["More terms from _Seiichi Manyama_, May 22 2017"], "references": 7, "revision": 12, "time": "2017-05-29T09:11:28-04:00", "created": "1999-12-11T03:00:00-05:00"}]}