{"greeting": "Greetings from The On-Line Encyclopedia of Integer Sequences! http://oeis.org/", "query": "id:A064230", "count": 1, "start": 0, "results": [{"number": 64230, "data": "1,1,1,1,9,6,1,49,288,174,1,225,6750,36000,22560,1,961,118800,3159750,17760600,12514320,1,3969,1807806,190071000,5295204600,34395777360,28836612000,1,16129,25316928,9271660734,1001080231200,32307576315840", "name": "Triangle T(n,k) = number of rational (0,1) matrices of rank k (n >= 0, 0 <= k <= n).", "comment": ["Rows add to 2^(n^2).", "Komlos and later Kahn, Komlos and Szemeredi show that almost all such matrices are invertible.", "Table 3 from M. Zivkovic, Classification of small (0,1) matrices (see link). - _Vladeta Jovovic_, Mar 28 2006"], "reference": ["J. Kahn, J. Komlos and E. Szemeredi: On the probability that a random +-1 matrix is singular, J. AMS 8 (1995), 223-240.", "J. Komlos, On the determinants of random matrices, Studia Sci. Math. Hungar., 3 (1968), 387-399."], "link": ["M. Zivkovic, <a href=\"http://arXiv.org/abs/math.CO/0511636\">Classification of small (0,1) matrices</a>, Linear Algebra and its Applications, 414 (2006), 310-346."], "example": ["1; 1,1; 1,9,6; 1,49,288,174; ..."], "program": ["(PARI) T=matrix(5,5); { for(n=0,4, mm=matrix(n,n); for(k=0,n,T[1+n,1+k]=0); forvec(x=vector(n*n,i,[0,1]), for(i=1,n, for(j=1,n,mm[i,j]=x[i+n*(j-1)])); T[1+n,1+matrank(mm)]++); for(k=0,n,print1(T[1+n,1+k], if(k<n,\",\",\"; \")));) }"], "xref": ["Cf. A064231, A000409, A000410, A046747."], "keyword": "nonn,nice,tabl", "offset": "0,5", "author": "_N. J. A. Sloane_, Sep 23 2001", "ext": ["More terms and PARI code from _Michael Somos_, Sep 25, 2001", "6 more terms from Lambert Klasen (Lambert.Klasen(AT)gmx.net), Dec 17 2004", "More terms from _Vladeta Jovovic_, Mar 28 2006"], "references": 3, "revision": 10, "time": "2014-04-30T01:37:33-04:00", "created": "2003-05-16T03:00:00-04:00"}]}