{"greeting": "Greetings from The On-Line Encyclopedia of Integer Sequences! http://oeis.org/", "query": "id:A077909", "count": 1, "start": 0, "results": [{"number": 77909, "data": "1,0,0,-1,2,0,1,-4,4,-1,6,-12,9,-8,24,-33,26,-40,81,-92,92,-161,254,-276,345,-576,784,-897,1266,-1936,2465,-3060,4468,-6337,7990,-10588,15273,-20664,26568,-36449,51210,-67896,89585,-124108,170316,-225377,303278,-418532,566009,-754032,1025088", "name": "Expansion of 1/((1-x)*(1+x+x^2+2*x^3)).", "comment": ["The absolute value of a(n) is the number of tilings of a 5 X n rectangle using n pentominoes of shapes N, U, X. |a(3)| = 1, |a(4)| = 2:", "._____.     ._______.  ._______.", "| ._. |     | ._. | |  | | ._. |", "|_| |_|     |_| |_| |  | |_| |_|", "|_. ._|  ,  | ._| ._|  |_. |_. |", "| |_| |     | | |_| |  | |_| | |", "|_____|     |_|_____|  |_____|_|. - _Alois P. Heinz_, Jan 03 2014"], "link": ["Alois P. Heinz, <a href=\"/A077909/b077909.txt\">Table of n, a(n) for n = 0..1000</a>", "Wikipedia, <a href=\"https://en.wikipedia.org/wiki/Pentomino\">Pentomino</a>", "<a href=\"/index/Rec#order_04\">Index entries for linear recurrences with constant coefficients</a>, signature (0,0,-1,2)"], "formula": ["a(n) = (-1)^n*sum(A128099(n-2*k, n-3*k), k=0..floor(n/3)). - _Johannes W. Meijer_, Aug 28 2013", "G.f.: 1/(1 + x^3 - 2*x^4). - _Arkadiusz Wesolowski_, Nov 20 2013"], "maple": ["a:= n-> (<<0|1|0|0>, <0|0|1|0>, <0|0|0|1>, <2|-1|0|0>>^n.", "        <<1, 0, 0, -1>>)[1, 1]:", "seq(a(n), n=0..60);  # _Alois P. Heinz_, Nov 20 2013"], "mathematica": ["CoefficientList[1/(1+x^3-2*x^4) + O[x]^60, x] (* _Jean-Fran\u00e7ois Alcover_, Jun 08 2015, after _Arkadiusz Wesolowski_ *)"], "program": ["(PARI) Vec( 1/((1-x)*(1+x+x^2+2*x^3)) +O(x^66)) \\\\ _Joerg Arndt_, Aug 28 2013"], "xref": ["Partial sums of A077976.", "Cf. A174249, A233427, A234312, A234931, A247126."], "keyword": "sign,easy", "offset": "0,5", "author": "_N. J. A. Sloane_, Nov 17 2002", "references": 5, "revision": 34, "time": "2017-02-06T18:54:40-05:00", "created": "2003-05-16T03:00:00-04:00"}]}