{"greeting": "Greetings from The On-Line Encyclopedia of Integer Sequences! http://oeis.org/", "query": "id:A078106", "count": 1, "start": 0, "results": [{"number": 78106, "data": "0,0,0,1,2,4,6,8,10,17,19,28,36,46,57,63,63,75,93,123,125,119", "name": "Number of distances not measured by the shortest Golomb ruler with n marks (i.e., length of shortest Golomb ruler with n marks minus number of distances measured by that ruler.", "comment": ["Appears to be (length of shortest Golomb ruler with n marks) - n*(n-1)/2; or A003022(n) - A000217(n-1)."], "reference": ["Miller, J. C. P. Difference bases. Three problems in additive number theory. Computers in number theory (Proc. Sci. Res. Council Atlas Sympos. No. 2, Oxford, 1969), pp. 299--322. Academic Press, London,1971. MR0316269 (47 #4817) - From _N. J. A. Sloane_, Jun 05 2012", "Rhys Price Jones, Gracelessness, Proc. 10th S.-E. Conf. Combin., Graph Theory and Computing, 1979, pp. 547-552. - From _N. J. A. Sloane_, Jun 05 2012"], "link": ["<a href=\"/index/Go#Golomb\">Index entries for sequences related to Golomb rulers</a>"], "xref": ["Cf. A000217, A003022, A106683."], "keyword": "nonn", "offset": "2,5", "author": "Michael Gilleland, Nov 24 2002", "ext": ["Made consistent with A003022 by _Peter Munn_, Jul 23 2019"], "references": 2, "revision": 14, "time": "2019-07-25T00:20:11-04:00", "created": "2003-05-16T03:00:00-04:00"}]}