{"greeting": "Greetings from The On-Line Encyclopedia of Integer Sequences! http://oeis.org/", "query": "id:A085694", "count": 1, "start": 0, "results": [{"number": 85694, "data": "1,2,2,2,3,2,2,3,2,2,3,3,3,3,4,2,2,3,2,2,3,3,3,3,4,2,2,3,2,2,3,3,3,3,4,3,3,3,4,3,3,3,4,3,3,3,4,4,4,4,4,5,2,2,3,2,2,3,3,3,3,4,2,2,3,2,2,3,3,3,3,4,3,3,3,4,3,3,3,4,3,3,3,4,4,4,4,4,5,2,2,3,2,2,3,3,3,3,4", "name": "Let f(0) = 1, f(1) = 12, f(2) = 223, f(3) = 3334, f(4) = 44445, f(5) = 555556, etc. Sequence gives limiting value of f(0), f(f(0)), f(f(f(0))), ...", "comment": ["The positions where 1, 2, 3, 4, 5, . . . appear are 1, 2, 5, 15, 52, . . . (Bell numbers A000110)."], "xref": ["Cf. A085693, A000110, A048993 = the number of occurrences of k in n-th block."], "keyword": "nonn,easy", "offset": "1,2", "author": "_Philippe Del\u00e9ham_, Aug 14, 2003; extended Jun 10 2005", "references": 1, "revision": 5, "time": "2013-02-22T14:38:47-05:00", "created": "2003-09-13T03:00:00-04:00"}]}