{"greeting": "Greetings from The On-Line Encyclopedia of Integer Sequences! http://oeis.org/", "query": "id:A091193", "count": 1, "start": 0, "results": [{"number": 91193, "data": "1,12,24,36,60,72,168,120,180,288,240,432,504,360,864,1296,960,840,720,1080,3456,1800,2016,1440,1680,3024,2160,3780,2880,2520,5280,3360,6048,4320,6480,22440,11340,7200,6720,7920,5040,10800,7560,12960,18900,13440", "name": "Smallest number having n abundant divisors.", "comment": ["A080224(a(n))=n and A080224(m)<>n for m<a(n)."], "link": ["Amiram Eldar, <a href=\"/A091193/b091193.txt\">Table of n, a(n) for n = 0..1000</a>", "Eric Weisstein's World of Mathematics, <a href=\"http://mathworld.wolfram.com/AbundantNumber.html\">Abundant Number</a>."], "mathematica": ["numd[n_] := Length@Select[Divisors[n], DivisorSigma[1, #] > 2 # &]; m = 100; s =", "Table[0, {m}]; n = 1; c = 0; While[c < m, k = numd[n]; If[k > 0 && k <= m && s[[k]] == 0, s[[k]] = n; c++]; n++]; s (* _Amiram Eldar_, Jun 24 2019 *)"], "xref": ["Cf. A080224."], "keyword": "nonn", "offset": "0,2", "author": "_Reinhard Zumkeller_, Dec 27 2003", "ext": ["More terms from _Reinhard Zumkeller_, Dec 12 2009"], "references": 4, "revision": 10, "time": "2019-06-24T04:01:14-04:00", "created": "2004-02-19T03:00:00-05:00"}]}