{"greeting": "Greetings from The On-Line Encyclopedia of Integer Sequences! http://oeis.org/", "query": "id:A114848", "count": 1, "start": 0, "results": [{"number": 114848, "data": "1,1,2,4,1,10,4,28,13,1,82,44,6,248,153,27,1,770,536,116,8,2440,1889,486,46,1,7858,6696,1992,240,10,25644,23849,8042,1180,70,1,84618,85276,32124,5552,430,12,281844,305933,127287,25306,2430,99,1,946338,1100692", "name": "Triangle read by rows T(n,k) = the number of Dyck paths of semilength n with k UUDDU's, 0<=k<=[(n-1)/2].", "comment": ["Row sums are Catalan numbers A000108."], "link": ["Alois P. Heinz, <a href=\"/A114848/b114848.txt\">Rows n = 0..200, flattened</a>", "A. Sapounakis, I. Tasoulas and P. Tsikouras, <a href=\"http://dx.doi.org/10.1016/j.disc.2007.03.005\">Counting strings in Dyck paths</a>, Discrete Math., 307 (2007), 2909-2924. - From _N. J. A. Sloane_, May 05 2012"], "formula": ["T(n,k) = Sum((-1)^j * binomial(n-1-(j+k), j+k) * binomial(j + k, k) * A000108(n-2(j+k)), j=0..[(n-1)/2]-k).", "G.f. G = G(t,z) satisfies G = C(z/(z^2(1-t)+1)), where C(z) is g.f. of Catalan numbers."], "example": ["T(4,1) = 4 because there exist 4 Dyck paths with one occurrence of UUDDU : UDUUDDUD, UUDDUDUD, UUDDUUDD, UUUDDUDD.", "Triangle begins:", ":  0 :     1;", ":  1 :     1;", ":  2 :     2;", ":  3 :     4,     1;", ":  4 :    10,     4;", ":  5 :    28,    13,     1;", ":  6 :    82,    44,     6;", ":  7 :   248,   153,    27,    1;", ":  8 :   770,   536,   116,    8;", ":  9 :  2440,  1889,   486,   46,   1;", ": 10 :  7858,  6696,  1992,  240,  10;", ": 11 : 25644, 23849,  8042, 1180,  70,  1;", ": 12 : 84618, 85276, 32124, 5552, 430, 12;"], "maple": ["b:= proc(x, y, t) option remember; `if`(y<0 or y>x, 0,", "     `if`(x=0, 1, expand(b(x-1, y+1, [2, 3, 3, 2, 2][t])", "      *`if`(t=5, z, 1) +b(x-1, y-1, [1, 1, 4, 5, 1][t]))))", "    end:", "T:= n-> (p-> seq(coeff(p, z, i), i=0..degree(p)))(b(2*n, 0, 1)):", "seq(T(n), n=0..15);  # _Alois P. Heinz_, Jun 10 2014"], "mathematica": ["For[n = 1, n <= 20, n++, For[k = 0, k <= Floor[(n - 1)/2], k++, Print[Sum[(-1)^j * Binomial[n - 1 - (j + k), j + k] * Binomial[j + k, k] * Binomial[2(n - 2(j + k)), n - 2(j + k)]/(n - 2(j + k) + 1), {j, 0, Floor[(n - 1)/2] - k}]]]]"], "xref": ["Cf. A187256, A243752."], "keyword": "nonn,tabf", "offset": "0,3", "author": "I. Tasoulas (jtas(AT)unipi.gr), Feb 20 2006", "references": 3, "revision": 20, "time": "2016-03-31T21:02:21-04:00", "created": "2006-02-24T03:00:00-05:00"}]}