{"greeting": "Greetings from The On-Line Encyclopedia of Integer Sequences! http://oeis.org/", "query": "id:A144464", "count": 1, "start": 0, "results": [{"number": 144464, "data": "1,1,1,1,2,1,1,2,2,1,1,2,4,2,1,1,2,4,4,2,1,1,2,4,8,4,2,1,1,2,4,8,8,4,2,1,1,2,4,8,16,8,4,2,1,1,2,4,8,16,16,8,4,2,1,1,2,4,8,16,32,16,8,4,2,1", "name": "Triangle T(n,m) read by rows: T(n,m) = 2^min(m,n-m).", "formula": ["Row sums: sum_{m=0..n} T(n,m) = A027383(n).", "T(n,k) = 2^A004197(n,k). - _Philippe Del\u00e9ham_, Feb 25 2014"], "example": ["The triangle starts in row n=0 as:", "{1},", "{1, 1},", "{1, 2, 1},", "{1, 2, 2, 1},", "{1, 2, 4, 2, 1},", "{1, 2, 4, 4, 2, 1},", "{1, 2, 4, 8, 4, 2, 1},", "{1, 2, 4, 8, 8, 4, 2, 1},", "{1, 2, 4, 8, 16, 8, 4, 2, 1},", "{1, 2, 4, 8, 16, 16, 8, 4, 2, 1},", "{1, 2, 4, 8, 16, 32, 16, 8, 4, 2, 1}"], "mathematica": ["Clear[f, t]; f[n_, m_] = If[m <= Floor[n/2], m, n - m]; Table[Table[f[n, m], {m, 0, n}], {n, 0, 10}]; Flatten[%]"], "program": ["(PARI) T(n,m)=1<<min(m,n-m) \\\\ _Charles R Greathouse IV_, Jan 15 2012"], "xref": ["Cf. A004197, A152714, A152716, A152717."], "keyword": "nonn,easy,tabl", "offset": "0,5", "author": "_Roger L. Bagula_ and _Gary W. Adamson_, Oct 09 2008", "ext": ["Offset corrected by the Associate Editors of the OEIS, Sep 11 2009", "Better name by _Philippe Del\u00e9ham_, Feb 25 2014"], "references": 8, "revision": 13, "time": "2014-02-25T06:52:58-05:00", "created": "2009-01-09T03:00:00-05:00"}]}