{"greeting": "Greetings from The On-Line Encyclopedia of Integer Sequences! http://oeis.org/", "query": "id:A245836", "count": 1, "start": 0, "results": [{"number": 245836, "data": "0,2,1,8,4,8,4,24,12,18,9,28,14,22,11,64,32,42,21,56,28,40,20,80,40,54,27,72,36,52,26,160,80,98,49,120,60,80,40,152,76,98,49,124,62,86,43,208,104,130,65,160,80,108,54,200,100,130,65,164,82,114,57", "name": "Row sums in triangle A053398 (Kopper's Nim values).", "comment": ["a(2*n) = 2*a(2*n+1)."], "link": ["Reinhard Zumkeller, <a href=\"/A245836/b245836.txt\">Table of n, a(n) for n = 1..1000</a>"], "program": ["(Haskell)", "a245836 = sum . a053398_row"], "keyword": "nonn", "offset": "1,2", "author": "_Reinhard Zumkeller_, Aug 04 2014", "references": 2, "revision": 7, "time": "2014-08-04T08:33:14-04:00", "created": "2014-08-04T08:26:45-04:00"}]}