{"greeting": "Greetings from The On-Line Encyclopedia of Integer Sequences! http://oeis.org/", "query": "id:A265896", "count": 1, "start": 0, "results": [{"number": 265896, "data": "1,3,2,6,4,5,7,10,11,8,29,9,22,12,16,15,37,17,46,13,56,38,191,14,79,30,92,18,254,23,232,21,137,47,326,24,172,57,67,19,211,68,121,48,106,212,277,20,301,93,154,39,352,107,379,25,407,278,1541,31,466,255,704,28,2081,155,1654,58,1082,353,2702,32,667,192,497,69,1712,80,781,26,821", "name": "Inverse permutation to A265895: a(n) = A265346(A263273(n)).", "link": ["Antti Karttunen, <a href=\"/A265896/b265896.txt\">Table of n, a(n) for n = 1..10328</a>", "<a href=\"/index/Per#IntegerPermutation\">Index entries for sequences that are permutations of the natural numbers</a>"], "formula": ["a(n) = A265346(A263273(n))."], "program": ["(Scheme) (define (A265896 n) (A265346 (A263273 n)))"], "xref": ["Inverse permutation of A265895.", "Cf. A263273, A265346 (cf. the scatter plot)."], "keyword": "nonn,base,look", "offset": "1,2", "author": "_Antti Karttunen_, Dec 18 2015", "references": 2, "revision": 10, "time": "2015-12-29T19:14:40-05:00", "created": "2015-12-29T03:23:31-05:00"}]}