{"greeting": "Greetings from The On-Line Encyclopedia of Integer Sequences! http://oeis.org/", "query": "id:A281458", "count": 1, "start": 0, "results": [{"number": 281458, "data": "1,0,1,0,0,0,0,0,0,1,0,1,0,0,0,0,1,0,1,0,0,0,0,1,0,2,0,1,0,0,1,0,2,0,1,0,0,1,0,3,0,2,0,0,1,0,3,0,3,0,1,1,0,4,0,4,0,1,1,0,4,0,5,0,2,1,0,5,0,7,0,3,1,0,5,0,8,0,5,1,1,6,0,10,0,6", "name": "Expansion of Product_{k>=1} (1 + x^(7*k-5)).", "link": ["Vaclav Kotesovec, <a href=\"/A281458/b281458.txt\">Table of n, a(n) for n = 0..10000</a>"], "formula": ["a(n) ~ exp(sqrt(n/21)*Pi) / (2^(9/7)*21^(1/4)*n^(3/4)) * (1 - (3*sqrt(21)/(8*Pi) + 11*Pi/(336*sqrt(21))) / sqrt(n)). - _Vaclav Kotesovec_, Jan 22 2017, extended Jan 24 2017"], "mathematica": ["nmax = 100; CoefficientList[Series[Product[(1 + x^(7*k - 5)), {k, 1, nmax}], {x, 0, nmax}], x]", "nmax = 100; poly = ConstantArray[0, nmax + 1]; poly[[1]] = 1; poly[[2]] = 0; Do[If[Mod[k, 7] == 2, Do[poly[[j + 1]] += poly[[j - k + 1]], {j, nmax, k, -1}]; ], {k, 2, nmax}]; poly"], "xref": ["Cf. A109704, A281245, A281455, A281456, A281457, A280457."], "keyword": "nonn", "offset": "0,26", "author": "_Vaclav Kotesovec_, Jan 22 2017", "references": 8, "revision": 6, "time": "2017-01-24T09:56:49-05:00", "created": "2017-01-22T05:25:10-05:00"}]}