{"greeting": "Greetings from The On-Line Encyclopedia of Integer Sequences! http://oeis.org/", "query": "id:A304042", "count": 1, "start": 0, "results": [{"number": 304042, "data": "1,1,1,1,1,1,1,1,1,1,1,1,1,1,1,1,1,1,1,1,1,1,1,1,1,1,1,1,1,1,1,1,1,1,1,1,1,1,1,1,1,1,1,1,1,1,1,1,1,1,1,1,1,1,1,1,1,1,1,1,1,1,1,1,1,1,1,5,1,1,1,5,1,1,1,1,1,1,1,3,1,3,1,1,1,1,1,1,1,1,1", "name": "Triangle read by rows: T(n,k) is the denominator of R(n,k) defined implicitly by the identity Sum_{i=0..l-1} Sum_{j=0..m} R(m,j)*(l-i)^j*i^j = l^(2*m+1) holding for all l,m >= 0.", "link": ["Antti Karttunen, <a href=\"/A304042/b304042.txt\">Table of n, a(n) for n = 0..10439 (the first 144 rows of triangle)</a>", "P.-Y. Huang, S.-C. Liu, and Y.-N. Yeh, <a href=\"https://doi.org/10.37236/3693\">Congruences of Finite Summations of the Coefficients in certain Generating Functions</a>, The Electronic Journal of Combinatorics, 21 (2014), #P2.45.", "C. Jordan, <a href=\"https://oeis.org/A002457/a002457_1.pdf\">Calculus of Finite Differences</a>, Budapest, 1939. [Annotated scans of pages 448-450 only]", "Petro Kolosov, <a href=\"https://arxiv.org/abs/1603.02468\">On the link between Binomial Theorem and Discrete Convolution of Power Function</a>, arXiv:1603.02468 [math.NT], 2016-2020.", "Petro Kolosov, <a href=\"https://kolosovpetro.github.io/pdf/coefficients_of_polynomial.pdf\">Definition and table of values</a>.", "Petro Kolosov, <a href=\"https://arxiv.org/abs/2101.00227\">An unusual identity for odd-powers</a>, arXiv:2101.00227 [math.GM], 2021.", "MathOverflow, <a href=\"https://mathoverflow.net/q/297900\">Discussion of these coefficients</a>, 2018."], "formula": ["Recurrence given by _Max Alekseyev_ (see the MathOverflow link):", "R(n, k) = 0 if k < 0 or k > n.", "R(n, k) = (2k+1)*binomial(2k, k) if k = n.", "R(n, k) = (2k+1)*binomial(2k, k)*Sum_{j=2k+1..n} R(n, j)*binomial(j, 2k+1)*(-1)^(j-1)/(j-k)*Bernoulli(2j-2k), otherwise.", "T(n, k) = denominator(R(n, k))."], "example": ["Triangle begins:", "-----------------------------------------------------", "k=    0  1  2  3  4  5  6  7  8  9  10 11 12 13 14 15", "-----------------------------------------------------", "n=0:  1;", "n=1:  1, 1;", "n=2:  1, 1, 1;", "n=3:  1, 1, 1, 1;", "n=4:  1, 1, 1, 1, 1;", "n=5:  1, 1, 1, 1, 1, 1;", "n=6:  1, 1, 1, 1, 1, 1, 1;", "n=7:  1, 1, 1, 1, 1, 1, 1, 1;", "n=8:  1, 1, 1, 1, 1, 1, 1, 1, 1;", "n=9:  1, 1, 1, 1, 1, 1, 1, 1, 1, 1;", "n=10: 1, 1, 1, 1, 1, 1, 1, 1, 1, 1, 1;", "n=11: 1, 5, 1, 1, 1, 5, 1, 1, 1, 1, 1, 1;", "n=12: 1, 3, 1, 3, 1, 1, 1, 1, 1, 1, 1, 1, 1;", "n=13: 1, 1, 1, 1, 1, 1, 1, 1, 1, 1, 1, 1, 1, 1;", "n=14: 1, 1, 1, 1, 1, 1, 1, 1, 1, 1, 1, 1, 1, 1, 1;", "n=15: 1, 1, 1, 1, 1, 1, 1, 1, 1, 1, 1, 1, 1, 1, 1, 1;"], "mathematica": ["R[n_, k_] := 0", "R[n_, k_] := (2 k + 1)*Binomial[2 k, k]*", "   Sum[R[n, j]*Binomial[j, 2 k + 1]*(-1)^(j - 1)/(j - k)*", "   BernoulliB[2 j - 2 k], {j, 2 k + 1, n}] /; 2 k + 1 <= n", "R[n_, k_] := (2 n + 1)*Binomial[2 n, n] /; k == n;", "T[n_, k_] := Denominator[R[n, k]];", "(* Print Fifteen Initial rows of Triangle A304042 *)", "Column[ Table[ T[n, k], {n, 0, 15}, {k, 0, n}], Center]"], "program": ["(PARI)", "up_to = 1274; \\\\ = binomial(50+1,2)-1", "A304042aux(n, k) = if((k<0)||(k>n),0,(k+k+1)*binomial(2*k, k)*if(k==n,1,sum(j=k+k+1,n, A304042aux(n, j)*binomial(j, k+k+1)*((-1)^(j-1))/(j-k)*bernfrac(2*(j-k)))));", "A304042tr(n, k) = denominator(A304042aux(n, k));", "A304042list(up_to) = { my(v = vector(up_to), i=0); for(n=0,oo, for(k=0,n, if(i++ > up_to, return(v)); v[i] = A304042tr(n,k))); (v); };", "v304042 = A304042list(1+up_to);", "A304042(n) = v304042[1+n]; \\\\ _Antti Karttunen_, Nov 07 2018"], "xref": ["Numerators are shown in A302971.", "Cf. A287326, A300656, A300785, A007318, A027641, A027642, A055012, A077028, A000146, A002882, A003245, A127187, A127188, A074909, A164555."], "keyword": "nonn,tabl,frac", "offset": "0,68", "author": "_Kolosov Petro_, May 05 2018", "references": 9, "revision": 38, "time": "2021-01-05T05:04:42-05:00", "created": "2018-05-05T17:34:49-04:00"}]}