{"greeting": "Greetings from The On-Line Encyclopedia of Integer Sequences! http://oeis.org/", "query": "id:A321009", "count": 1, "start": 0, "results": [{"number": 321009, "data": "2,4,12,48,240,10,70,560,54,540,5940,71280,9240,129360,19,304,5168,93024,145,29,609,198,0", "name": "a(1)=2; thereafter a(n) is obtained by applying Eric Angelini's remove-repeated-digits map, x->A320486(x), to n*a(n-1), stopping when 0 is reached.", "reference": ["Eric Angelini, Posting to Sequence Fans Mailing List, Oct 24 2018"], "example": ["a(5)=240, so for a(6) we compute 6*240 = 1440 which becomes 10 = a(6)."], "xref": ["Cf. A320485, A320486, A321008."], "keyword": "nonn,base,fini,full", "offset": "1,1", "author": "_N. J. A. Sloane_, Nov 03 2018", "references": 1, "revision": 9, "time": "2019-04-10T01:25:39-04:00", "created": "2018-11-03T23:41:16-04:00"}]}