{"greeting": "Greetings from The On-Line Encyclopedia of Integer Sequences! http://oeis.org/", "query": "id:A328985", "count": 1, "start": 0, "results": [{"number": 328985, "data": "2,4,-2,6,-3,9,-7,11,-8,14,-12,16,-13,19,-17,21,-18,24,-22,26,-23,29,-27,31,-28,34,-32,36,-33,39,-37,41,-38,44,-42,46,-43,49,-47,51,-48,54,-52,56,-53,59,-57,61,-58,64,-62,66,-63,69,-67,71,-68,74", "name": "First differences of A328984.", "comment": ["This is a simplified version of A328196.", "Conjecture: satisfies a linear recurrence having signature (-1, 0, 0, 1, 1). - _Harvey P. Dale_, Apr 06 2021"], "formula": ["If n is a multiple of 4 then a(n) = 5*t+1 where t = n/4;", "if n is 2 mod 4 then a(n) = 5*t+4 where t = (n-2)/4;", "if n is 1 mod 4 then a(n) = -(5*t-2) where t = (n-1)/4;", "if n i s 3 mod 4 then a(n) = -(5*t+2) where t = (n-3)/4.", "From _Colin Barker_, Nov 07 2019: (Start)", "G.f.: x*(2 + 6*x + 2*x^2 + 4*x^3 + x^4) / ((1+x)*(1-x^4)).", "a(n) = -a(n-1) + a(n-4) + a(n-5) for n>5.", "(End)"], "mathematica": ["Differences[Table[Which[EvenQ[n],Floor[(5 n/2+1)/2],Mod[n,4]==1,10 (n-1)/4+1,True,10 (n-3)/4+7],{n,70}]] (* _Harvey P. Dale_, Apr 06 2021 *)"], "xref": ["Cf. A328190, A328196, A328984."], "keyword": "sign", "offset": "1,1", "author": "_N. J. A. Sloane_, Nov 06 2019", "references": 3, "revision": 12, "time": "2021-04-06T14:36:26-04:00", "created": "2019-11-06T21:01:39-05:00"}]}