{"greeting": "Greetings from The On-Line Encyclopedia of Integer Sequences! http://oeis.org/", "query": "id:A329197", "count": 1, "start": 0, "results": [{"number": 329197, "data": "5,6,3,7,5,9,6,3,3,5,3,3,6,3,3,3,5,3,3,6,3,3,3,3,5,3,3,6,3,17,3,11,3,3,3,5,3,3,6,6,3,17,3,3,3,3,5,7,6", "name": "Length of the n-th nontrivial cycle of the \"ghost iteration\" A329200.", "comment": ["A329200 consists in adding or subtracting the number A040115(n) whose digits are the differences of adjacent digits of n, depending on its parity.", "Repdigits A010785 are fixed points of this map, but some numbers enter nontrivial cycles. This sequence gives the length of these cycles, ordered by their smallest member, as they are listed in the table A329196. See there for more information."], "example": ["The first cycle of A329200 is row 1 of A329196, (8290, 8969, 9102), of length 3 = a(1).", "The second cycle of A329200 is row 2 of A329196, (17998, 24199, 21819, 20041, 22084, 21800, 20020), of length 7 = a(2)."], "program": ["(PARI) /* change T to #T in print statement of code for A329196 */"], "xref": ["Cf. A329196, A329200, A329198, A329342 (variant using A329201)."], "keyword": "nonn,more", "offset": "1,1", "author": "_M. F. Hasler_, Nov 10 2019", "ext": ["a(9)-a(35) from _Scott R. Shannon_, Nov 12 2019", "a(36)-a(49) from _Lars Blomberg_, Nov 15 2019"], "references": 10, "revision": 21, "time": "2019-11-16T13:59:34-05:00", "created": "2019-11-11T00:28:57-05:00"}]}